spdl/io/__init__.py
spdl/io/__init__.pyi
spdl/io/_array.py
spdl/io/_composite.py
spdl/io/_config.py
spdl/io/_convert.py
spdl/io/_core.py
spdl/io/_preprocessing.py
spdl/io/_tar.py
spdl/io/_transfer.py
spdl/io/_wav.py
spdl/io/_internal/__init__.py
spdl/io/_internal/import_utils.py
spdl/io/lib/__init__.py
spdl/io/lib/_archive.cpython-314t-aarch64-linux-gnu.so
spdl/io/lib/_archive.pyi
spdl/io/lib/_libspdl.pyi
spdl/io/lib/_libspdl_cuda.pyi
spdl/io/lib/_spdl_cuda4.cpython-314t-aarch64-linux-gnu.so
spdl/io/lib/_spdl_cuda5.cpython-314t-aarch64-linux-gnu.so
spdl/io/lib/_spdl_cuda6.cpython-314t-aarch64-linux-gnu.so
spdl/io/lib/_spdl_cuda7.cpython-314t-aarch64-linux-gnu.so
spdl/io/lib/_spdl_cuda8.cpython-314t-aarch64-linux-gnu.so
spdl/io/lib/_spdl_ffmpeg4.cpython-314t-aarch64-linux-gnu.so
spdl/io/lib/_spdl_ffmpeg5.cpython-314t-aarch64-linux-gnu.so
spdl/io/lib/_spdl_ffmpeg6.cpython-314t-aarch64-linux-gnu.so
spdl/io/lib/_spdl_ffmpeg7.cpython-314t-aarch64-linux-gnu.so
spdl/io/lib/_spdl_ffmpeg8.cpython-314t-aarch64-linux-gnu.so
spdl/io/lib/_wav.cpython-314t-aarch64-linux-gnu.so
spdl/io/lib/_wav.pyi
spdl/io/lib/libspdl_ffmpeg4.so
spdl/io/lib/libspdl_ffmpeg5.so
spdl/io/lib/libspdl_ffmpeg6.so
spdl/io/lib/libspdl_ffmpeg7.so
spdl/io/lib/libspdl_ffmpeg8.so
spdl/io/lib/stubgen.py
spdl/io/utils/__init__.py
spdl/io/utils/_build.py
spdl/io/utils/_ffmpeg.py
spdl/io/utils/_tracing.py
spdl_io-0.2.0.dist-info/METADATA
spdl_io-0.2.0.dist-info/WHEEL
spdl_io-0.2.0.dist-info/top_level.txt
spdl_io-0.2.0.dist-info/RECORD
spdl_io-0.2.0.dist-info/licenses/LICENSE
