Metadata-Version: 2.4
Name: spdl_io
Version: 0.2.0
Summary: SPDL plugin for loading media data into array format.
Author-email: Moto Hira <moto@meta.com>
License-Expression: BSD-2-Clause
Project-URL: Documentation, https://facebookresearch.github.io/spdl/main/index.html
Requires-Python: >=3.10
License-File: LICENSE
Requires-Dist: numpy>=1.21
Dynamic: license-file
